[{"Name":"Rootler","Score":100000},{"Name":"Player1","Score":6901},{"Name":"Player2","Score":8820},{"Name":"Player3","Score":7433},{"Name":"Player4","Score":9320},{"Name":"Player5","Score":1552},{"Name":"Player6","Score":214},{"Name":"Kendra","Score":2600},{"Name":"Rayhaan :):)","Score":8500},{"Name":"Justine","Score":15100},{"Name":"Ray beat Justine","Score":19200},{"Name":"Kendra","Score":11400},{"Name":"Finally, Testing is done :)","Score":2100},{"Name":"This is a score","Score":2700},{"Name":"This is a score","Score":6600},{"Name":"Kendra","Score":6600},{"Name":"a score","Score":2400}]